contextManager/__init__.py
contextManager/combined_types.py
contextManager/contextManager.py
contextManager/conversions.py
testing/__init__.py
testing/testing.py
mariadb_context_manager-1.0.0.dist-info/LICENSE.txt
mariadb_context_manager-1.0.0.dist-info/METADATA
mariadb_context_manager-1.0.0.dist-info/WHEEL
mariadb_context_manager-1.0.0.dist-info/top_level.txt
mariadb_context_manager-1.0.0.dist-info/RECORD
