Metadata-Version: 2.2
Name: MariaDB_Context_Manager
Version: 1.0.0
Summary: An easy to use mariadb context manager
Home-page: http://pypi.python.org/pypi/MariaDB-Context-Manager
Author: Antony
Author-email: Antony <antonygradillas@gmail.com>
Project-URL: Homepage, https://github.com/avgra3/MariaDB-Context-Manager
Project-URL: Issues, https://github.com/avgra3/MariaDB-Context-Manager/issues
Classifier: Programming Language :: Python :: 3
Classifier: License :: OSI Approved :: MIT License
Classifier: Operating System :: OS Independent
Requires-Python: >=3.9
License-File: LICENSE.txt
Requires-Dist: mariadb>=1.1.10
Dynamic: author
Dynamic: home-page
Dynamic: requires-python
